hctest_excel_to/__init__.py
hctest_excel_to/excel_to.py
hctest_excel_to-1.dist-info/METADATA
hctest_excel_to-1.dist-info/WHEEL
hctest_excel_to-1.dist-info/top_level.txt
hctest_excel_to-1.dist-info/RECORD
