Metadata-Version: 2.1
Name: hctest-excel-to
Version: 1
Summary: 读取Excel并转化为Python中的数据类型
Home-page: https://github.com/pypa/sampleproject
Author: cf
Author-email: dingjun_baby@yeah.net
Classifier: Programming Language :: Python :: 3
Classifier: License :: OSI Approved :: MIT License
Classifier: Operating System :: OS Independent
Requires-Python: >=3.6
Requires-Dist: xlrd (==1.2.0)
